LICENSE
MANIFEST.in
README.md
pyproject.toml
requirements-dev.txt
requirements.txt
setup.cfg
setup.py
versioneer.py
merlin/core/__init__.py
merlin/core/_version.py
merlin/core/dispatch.py
merlin/core/has_gpu.py
merlin/core/protocols.py
merlin/core/utils.py
merlin/core/compat/__init__.py
merlin/core/compat/tensorflow.py
merlin/core/compat/torch.py
merlin/dag/__init__.py
merlin/dag/executors.py
merlin/dag/graph.py
merlin/dag/node.py
merlin/dag/operator.py
merlin/dag/runtime.py
merlin/dag/selector.py
merlin/dag/utils.py
merlin/dag/ops/__init__.py
merlin/dag/ops/add_metadata.py
merlin/dag/ops/concat_columns.py
merlin/dag/ops/grouping.py
merlin/dag/ops/rename.py
merlin/dag/ops/selection.py
merlin/dag/ops/stat_operator.py
merlin/dag/ops/subgraph.py
merlin/dag/ops/subset_columns.py
merlin/dag/ops/subtraction.py
merlin/dag/ops/udf.py
merlin/dispatch/lazy.py
merlin/dtypes/__init__.py
merlin/dtypes/aliases.py
merlin/dtypes/base.py
merlin/dtypes/mapping.py
merlin/dtypes/registry.py
merlin/dtypes/shape.py
merlin/dtypes/mappings/__init__.py
merlin/dtypes/mappings/cudf.py
merlin/dtypes/mappings/merlin.py
merlin/dtypes/mappings/numpy.py
merlin/dtypes/mappings/pandas.py
merlin/dtypes/mappings/python.py
merlin/dtypes/mappings/tf.py
merlin/dtypes/mappings/torch.py
merlin/dtypes/mappings/triton.py
merlin/io/__init__.py
merlin/io/avro.py
merlin/io/csv.py
merlin/io/dask.py
merlin/io/dataframe_engine.py
merlin/io/dataframe_iter.py
merlin/io/dataset.py
merlin/io/dataset_engine.py
merlin/io/fsspec_utils.py
merlin/io/hugectr.py
merlin/io/parquet.py
merlin/io/shuffle.py
merlin/io/worker.py
merlin/io/writer.py
merlin/io/writer_factory.py
merlin/schema/__init__.py
merlin/schema/schema.py
merlin/schema/tags.py
merlin/schema/io/__init__.py
merlin/schema/io/proto_utils.py
merlin/schema/io/schema_bp.py
merlin/schema/io/tensorflow_metadata.py
merlin/table/__init__.py
merlin/table/conversions.py
merlin/table/cupy_column.py
merlin/table/numpy_column.py
merlin/table/tensor_column.py
merlin_core.egg-info/PKG-INFO
merlin_core.egg-info/SOURCES.txt
merlin_core.egg-info/dependency_links.txt
merlin_core.egg-info/not-zip-safe
merlin_core.egg-info/requires.txt
merlin_core.egg-info/top_level.txt