Metadata-Version: 2.1
Name: merlin-core
Version: 23.8.0
Summary: UNKNOWN
Home-page: https://github.com/NVIDIA-Merlin/core
Author: NVIDIA Corporation
License: Apache 2.0
Platform: UNKNOWN
Classifier: Development Status :: 4 - Beta
Classifier: Programming Language :: Python :: 3
Classifier: Intended Audience :: Developers
Classifier: License :: OSI Approved :: Apache Software License
Classifier: Topic :: Software Development :: Libraries
Classifier: Topic :: Scientific/Engineering
Requires-Python: >=3.8
License-File: LICENSE
